ucat/__init__.py
ucat-0.1.1.dist-info/LICENSE
ucat-0.1.1.dist-info/METADATA
ucat-0.1.1.dist-info/WHEEL
ucat-0.1.1.dist-info/top_level.txt
ucat-0.1.1.dist-info/RECORD
