Metadata-Version: 2.1
Name: ucat
Version: 0.1.1
Summary: Unit conversion for the abundance of atmospheric trace gases.
Home-page: https://gitlab.com/empa503/general-tools/u-cat
Author: Gerrit Kuhlmann
Author-email: gerrit.kuhlmann@empa.ch
License: UNKNOWN
Project-URL: Bug Tracker, https://gitlab.com/empa503/general-tools/u-cat/-/issues
Platform: UNKNOWN
Classifier: Programming Language :: Python :: 3
Classifier: License :: OSI Approved :: GNU Lesser General Public License v2 or later (LGPLv2+)
Classifier: Operating System :: OS Independent
Requires-Python: >=3.6
License-File: LICENSE
Requires-Dist: numpy
Requires-Dist: scipy
